django_debug_signals/__init__.py
django_debug_signals/apps.py
django_debug_signals-0.2.0.dist-info/METADATA
django_debug_signals-0.2.0.dist-info/WHEEL
django_debug_signals-0.2.0.dist-info/RECORD
