Metadata-Version: 2.4
Name: django-debug-signals
Version: 0.2.0
Summary: Help for debugging Django signal loading order.
Author-email: Paul Traylor <kungfudiscomonkey@gmail.com>
Requires-Python: >=3.8
Requires-Dist: django>=3.2
